proofassist/__init__.py
proofassist/main.py
symcollab/__init__.py
symcollab-0.1.1.dist-info/LICENSE
symcollab-0.1.1.dist-info/METADATA
symcollab-0.1.1.dist-info/WHEEL
symcollab-0.1.1.dist-info/top_level.txt
symcollab-0.1.1.dist-info/RECORD
