Metadata-Version: 2.1
Name: symcollab
Version: 0.1.1
Summary: UNKNOWN
Home-page: https://github.com/symcollab/cryptosolve
License: UNKNOWN
Platform: UNKNOWN
Requires-Dist: symcollab-algebra
Requires-Dist: symcollab-xor
Requires-Dist: symcollab-unification
Requires-Dist: symcollab-rewrite
Requires-Dist: symcollab-theories
Requires-Dist: symcollab-moe
